odoo/addons/fleet_config/README.rst
odoo/addons/fleet_config/__init__.py
odoo/addons/fleet_config/__manifest__.py
odoo/addons/fleet_config/i18n/fleet_config.pot
odoo/addons/fleet_config/i18n/it.po
odoo/addons/fleet_config/i18n/pt_BR.po
odoo/addons/fleet_config/readme/CONTRIBUTORS.rst
odoo/addons/fleet_config/readme/CREDITS.rst
odoo/addons/fleet_config/readme/DESCRIPTION.rst
odoo/addons/fleet_config/readme/USAGE.rst
odoo/addons/fleet_config/static/description/banner.png
odoo/addons/fleet_config/static/description/icon.png
odoo/addons/fleet_config/static/description/index.html
odoo/addons/fleet_config/views/res_config_settings.xml
odoo12_addon_fleet_config-12.0.1.0.0.99.dev8.dist-info/METADATA
odoo12_addon_fleet_config-12.0.1.0.0.99.dev8.dist-info/WHEEL
odoo12_addon_fleet_config-12.0.1.0.0.99.dev8.dist-info/top_level.txt
odoo12_addon_fleet_config-12.0.1.0.0.99.dev8.dist-info/RECORD
